tvmazetgbot/__init__.py
tvmazetgbot/__main__.py
tvmazetgbot/client.py
tvmazetgbot/database_tools.py
tvmazetgbot/tg_api.py
tvmazetgbot/tvmaze/__init__.py
tvmazetgbot/tvmaze/decorators.py
tvmazetgbot/tvmaze/tv_program.py
tvmazetgbot/tvmaze/tv_program_model.py
tvmazetgbot-0.1.0.dist-info/METADATA
tvmazetgbot-0.1.0.dist-info/WHEEL
tvmazetgbot-0.1.0.dist-info/top_level.txt
tvmazetgbot-0.1.0.dist-info/RECORD
