Metadata-Version: 2.1
Name: tvmazetgbot
Version: 0.1.0
Summary: Demo library
Home-page: UNKNOWN
Author: Andrei Y
Author-email: andrkool151@gmail.com
License: MIT
Platform: UNKNOWN
Classifier: Intended Audience :: Developers
Classifier: License :: OSI Approved :: MIT License
Classifier: Programming Language :: Python
Classifier: Programming Language :: Python :: 3
Classifier: Programming Language :: Python :: 3.6
Classifier: Programming Language :: Python :: 3.7
Classifier: Programming Language :: Python :: 3.8
Classifier: Programming Language :: Python :: 3.9
Classifier: Operating System :: OS Independent
Requires-Dist: pydantic (==1.10.2)
